galleries/__init__.py
galleries/files_utils.py
galleries/galleries_management.py
galleries/gallery.py
galleries/gallery_sql.py
galleries/igallery.py
galleries/annotations_filtering/__init__.py
galleries/annotations_filtering/filter.py
galleries/annotations_filtering/utils.py
galleries/annotations_parsers/__init__.py
galleries/annotations_parsers/file_name_parser.py
galleries/annotations_parsers/folder_parser.py
galleries/annotations_parsers/gallery_annots_parsers.py
galleries/collections/__init__.py
galleries/collections/file_stream_dictionary.py
galleries/collections/stream_dictionary.py
galleries/data_read_write/__init__.py
galleries/data_read_write/idata_reader_writer.py
galleries/data_read_write/pickle_data_reader_writer.py
galleries/data_read_write/sqlite_data_reader_writer.py
galleries/data_read_write/utils_file_data_readers_writers.py
galleries/images_providers/__init__.py
galleries/images_providers/gallery_images_provider.py
galleries/images_providers/local_files_image_providers.py
galleries/sql/__init__.py
galleries/sql/connectors/__init__.py
galleries/sql/connectors/connector.py
galleries/sql/connectors/oracle_connector.py
galleries/sql/connectors/sqlite_connector.py
galleries/sql/queries/__init__.py
galleries/sql/queries/data_retriever.py
test/__init__.py
test/data_reader_writer_tests.py
test/file_stream_dictionary_tests.py
test/stream_dictionary_tests.py
test/test_utils.py
test/test_utils_data_reading_writing.py
galleries-0.5.1.dist-info/LICENSE
galleries-0.5.1.dist-info/METADATA
galleries-0.5.1.dist-info/WHEEL
galleries-0.5.1.dist-info/top_level.txt
galleries-0.5.1.dist-info/RECORD
