Metadata-Version: 2.1
Name: galleries
Version: 0.5.1
Summary: Package to work with galleries of images
Home-page: https://github.com/mnicolas94/***
Author: Miguel Nicolás-Díaz
Author-email: miguelcok27@gmail.com
Classifier: Programming Language :: Python :: 3
Classifier: License :: OSI Approved :: MIT License
Classifier: Operating System :: OS Independent
Classifier: Development Status :: 3 - Alpha
Classifier: Intended Audience :: Developers
Requires-Python: >=3.6
License-File: LICENSE
Requires-Dist: cx-Oracle
Requires-Dist: jsonpickle
Requires-Dist: mnd-utils (>=0.1.7)
Requires-Dist: numpy
Requires-Dist: opencv-python
Requires-Dist: propsettings (>=0.1.15)
